pyhasse.lpom-0.2.1-py3.7-nspkg.pth
pyhasse/lpom/__init__.py
pyhasse/lpom/calc.py
pyhasse.lpom-0.2.1.dist-info/AUTHORS.rst
pyhasse.lpom-0.2.1.dist-info/LICENSE
pyhasse.lpom-0.2.1.dist-info/METADATA
pyhasse.lpom-0.2.1.dist-info/WHEEL
pyhasse.lpom-0.2.1.dist-info/namespace_packages.txt
pyhasse.lpom-0.2.1.dist-info/top_level.txt
pyhasse.lpom-0.2.1.dist-info/RECORD
