Metadata-Version: 2.1
Name: pyhasse.lpom
Version: 0.2.1
Summary: pyhasse-lpom: Synthetic indicator, without the need of weights for single indicators of a multi-indicator system
Home-page: https://pyhasse.org
Author: Rainer Bruggemann
Author-email: rainer.bruggemann@pyhasse.org
License: MIT license
Keywords: lpom
Platform: UNKNOWN
Classifier: Development Status :: 2 - Pre-Alpha
Classifier: Intended Audience :: Developers
Classifier: License :: OSI Approved :: MIT License
Classifier: Topic :: Scientific/Engineering :: Mathematics
Classifier: Natural Language :: English
Classifier: Programming Language :: Python :: 3.9
Requires-Dist: setuptools
Requires-Dist: pyhasse.core
